aioflask/__init__.py
aioflask/app.py
aioflask/asgi.py
aioflask/cli.py
aioflask/templating.py
aioflask/testing.py
tests/__init__.py
tests/test_aioflask.py
aioflask-0.3.0.dist-info/LICENSE
aioflask-0.3.0.dist-info/METADATA
aioflask-0.3.0.dist-info/WHEEL
aioflask-0.3.0.dist-info/entry_points.txt
aioflask-0.3.0.dist-info/top_level.txt
aioflask-0.3.0.dist-info/RECORD
