Metadata-Version: 2.1
Name: aioflask
Version: 0.3.0
Summary: Flask running on asyncio.
Home-page: https://github.com/miguelgrinberg/aioflask
Author: Miguel Grinberg
Author-email: miguel.grinberg@gmail.com
License: UNKNOWN
Project-URL: Bug Tracker, https://github.com/miguelgrinberg/aioflask/issues
Platform: UNKNOWN
Classifier: Intended Audience :: Developers
Classifier: Programming Language :: Python :: 3
Classifier: License :: OSI Approved :: MIT License
Classifier: Operating System :: OS Independent
Requires-Python: >=3.6
License-File: LICENSE
Requires-Dist: greenletio
Requires-Dist: flask (>=2)
Requires-Dist: uvicorn
